hey/__init__.py
hey/actions.py
hey/aichat.py
hey/cli.py
hey/helpers.py
hey/install.py
hey/parse.py
hey/prompt.chat.txt
hey/prompt.command.txt
hey/prompt.py
hey/prompt.start.txt
hey/plugins/chat/plugin.py
hey/plugins/chat/prompt.txt
hey/plugins/cli/plugin.py
hey/plugins/cli/prompt.txt
hey/plugins/lang/plugin.py
hey/plugins/lang/prompt.txt
hey/plugins/python/plugin.py
hey/plugins/python/prompt.txt
hey/prompt/command.txt
hey/prompt/question.txt
hey_gpt-1.1.4.dist-info/LICENSE
hey_gpt-1.1.4.dist-info/METADATA
hey_gpt-1.1.4.dist-info/WHEEL
hey_gpt-1.1.4.dist-info/entry_points.txt
hey_gpt-1.1.4.dist-info/top_level.txt
hey_gpt-1.1.4.dist-info/RECORD
