Metadata-Version: 2.1
Name: hey-gpt
Version: 1.1.4
Summary: Use OpenAI/ChatGPT gpt-3.5-turbo on the command-line
Home-page: https://github.com/lennardv2/hey-gpt-cli
Author: Lennard Voogdt
Author-email: lennard@spring.nl
License: MIT
Keywords: openai,chatgpt,ask,commandline,cli
Platform: UNKNOWN
Classifier: Development Status :: 5 - Production/Stable
Classifier: License :: OSI Approved :: MIT License
Classifier: Programming Language :: Python :: 3
License-File: LICENSE
Requires-Dist: pygments
Requires-Dist: simple-term-menu
Requires-Dist: prompt-toolkit
Requires-Dist: tiktoken
Requires-Dist: colorama
Requires-Dist: pyyaml
Requires-Dist: openai
Requires-Dist: distro
Requires-Dist: termcolor
